race_strategist/__init__.py
race_strategist/config.py
race_strategist/constants.py
race_strategist/main.py
race_strategist/recorder.py
race_strategist/runner.py
race_strategist/connectors/__init__.py
race_strategist/connectors/heart_beat_monitor.py
race_strategist/connectors/csv/__init__.py
race_strategist/connectors/influxdb/__init__.py
race_strategist/connectors/influxdb/connector.py
race_strategist/connectors/influxdb/processor.py
race_strategist/connectors/kafka/__init__.py
race_strategist/connectors/kafka/connector.py
race_strategist/connectors/kafka/processor.py
race_strategist/connectors/physical_sensors/__init__.py
race_strategist/connectors/physical_sensors/heart_beat_monitor.py
race_strategist/frontend/__init__.py
race_strategist/frontend/app.py
race_strategist/frontend/connectors/__init__.py
race_strategist/frontend/connectors/influxdb.py
race_strategist/modelling/__init__.py
race_strategist/modelling/packet_types.py
race_strategist/modelling/processor.py
race_strategist/packet_processing/__init__.py
race_strategist/packet_processing/packet_converter.py
race_strategist/packet_processing/packet_types.py
race_strategist/packet_processing/processor.py
race_strategist/session/__init__.py
race_strategist/session/session.py
race_strategist/telemetry/__init__.py
race_strategist/telemetry/constants.py
race_strategist/telemetry/listener.py
f1_2021_race_strategist-0.0.1.dist-info/LICENSE
f1_2021_race_strategist-0.0.1.dist-info/METADATA
f1_2021_race_strategist-0.0.1.dist-info/WHEEL
f1_2021_race_strategist-0.0.1.dist-info/entry_points.txt
f1_2021_race_strategist-0.0.1.dist-info/top_level.txt
f1_2021_race_strategist-0.0.1.dist-info/RECORD
